{"authorDailyContributionsMap":{"daynerss1":[{"date":"2026-01-23T00:00:00","commitResults":[{"hash":"bfe7dbb4c67005d67af397d4f6c9995b2c0c4405","isMergeCommit":false,"messageTitle":"Rename bot and implement skeletal version","messageBody":"","fileTypesAndContributionMap":{"java":{"insertions":9,"deletions":10}}}]}]},"authorFileTypeContributionMap":{"daynerss1":{"java":9,"md":0,"fxml":0,"sh":0,"bat":0,"gradle":0,"txt":0}},"authorContributionVariance":{"daynerss1":22.462223},"authorDisplayNameMap":{"daynerss1":"DAYN..XUAN"}}
