{"authorDailyContributionsMap":{"EnderSky":[{"date":"2026-01-23T00:00:00","commitResults":[{"hash":"0a9a7740981014da2851c3cedce1a43c654228f4","isMergeCommit":false,"messageTitle":"feat: renamed bot, added greet and exit text","messageBody":"","tags":["Level-0"],"fileTypesAndContributionMap":{"java":{"insertions":22,"deletions":10}}},{"hash":"471088afb36a35a0b8589384a3d526f857044a9d","isMergeCommit":false,"messageTitle":"feat: added echo","messageBody":"","tags":["Level-1"],"fileTypesAndContributionMap":{"java":{"insertions":40,"deletions":13}}},{"hash":"18bcb2be4b0d6019f7250c4c863a75d827947caa","isMergeCommit":false,"messageTitle":"feat: added list command","messageBody":"","tags":["Level-2"],"fileTypesAndContributionMap":{"java":{"insertions":29,"deletions":7}}},{"hash":"d3dd55349e6c187b77620e237ee5e2650548a274","isMergeCommit":false,"messageTitle":"feat: added task class","messageBody":"","tags":["A-Classes"],"fileTypesAndContributionMap":{"java":{"insertions":28,"deletions":2}}},{"hash":"088a92e80d24722a57fb59addf9119b9e2452bf7","isMergeCommit":false,"messageTitle":"feat: added mark as done","messageBody":"","tags":["Level-3"],"fileTypesAndContributionMap":{"java":{"insertions":23,"deletions":1}}},{"hash":"c8720d48b50ab28984272d5a24b9e8934d2075bb","isMergeCommit":false,"messageTitle":"feat: added todo, event, deadline","messageBody":"","tags":["A-Inheritance"],"fileTypesAndContributionMap":{"java":{"insertions":54,"deletions":4}}},{"hash":"aa49533e7a6eee48930b4755b7d071e9693a8ae5","isMergeCommit":false,"messageTitle":"feat: added todo, event, deadline","messageBody":"","tags":["Level-4"],"fileTypesAndContributionMap":{"java":{"insertions":45,"deletions":18}}}]},{"date":"2026-01-25T00:00:00","commitResults":[{"hash":"ed0ebef5ce82879db8b0c2bb66b1dce0937fd2a1","isMergeCommit":false,"messageTitle":"feat: added automated text UI testing","messageBody":"","tags":["A-TextUiTesting"],"fileTypesAndContributionMap":{"txt":{"insertions":9,"deletions":0},"java":{"insertions":2,"deletions":1},"bat":{"insertions":1,"deletions":1}}},{"hash":"43ee9ca3c3aba463133471375fcea4e8bbae0091","isMergeCommit":false,"messageTitle":"feat: added error handling","messageBody":"","tags":["Level-5"],"fileTypesAndContributionMap":{"java":{"insertions":71,"deletions":7}}},{"hash":"d1abe6efc00a92ddaa2b4671d56677de70bab5c3","isMergeCommit":false,"messageTitle":"feat: added delete feature","messageBody":"","tags":["Level-6"],"fileTypesAndContributionMap":{"java":{"insertions":40,"deletions":3}}}]},{"date":"2026-01-27T00:00:00","commitResults":[{"hash":"7d2530f2ba88caeb840d9e382d94ae95384f4980","isMergeCommit":false,"messageTitle":"refactor: used enums for command processing","messageBody":"","tags":["A-Enums"],"fileTypesAndContributionMap":{"java":{"insertions":162,"deletions":146}}}]},{"date":"2026-02-03T00:00:00","commitResults":[{"hash":"490bb9bd24215b5d0bfbc8226edd4fab8f594c78","isMergeCommit":false,"messageTitle":"Update README","messageBody":"","fileTypesAndContributionMap":{"md":{"insertions":16,"deletions":14}}},{"hash":"f3e9674df052f0c81216d889fe32064aae37f402","isMergeCommit":false,"messageTitle":"Add saving tasks to file","messageBody":"","fileTypesAndContributionMap":{"java":{"insertions":109,"deletions":13}}},{"hash":"c0bf95dfa7e1b358a58529280194b5968e961ce9","isMergeCommit":false,"messageTitle":"Add loading of task list from file","messageBody":"","fileTypesAndContributionMap":{"java":{"insertions":60,"deletions":13}}},{"hash":"b94b4b7fe70fb7846ad6b93debb8ee51dc52cd9f","isMergeCommit":true,"messageTitle":"Merge branch \u0027branch-Level-7\u0027 to \u0027main\u0027","messageBody":"","tags":["Level-7"],"fileTypesAndContributionMap":{}},{"hash":"c83c79621a3f859d08e3f41d3c686035e485a682","isMergeCommit":false,"messageTitle":"Add feature to store deadline as datetime objects","messageBody":"","fileTypesAndContributionMap":{"java":{"insertions":70,"deletions":8}}},{"hash":"2d0bf090b57b503d2735f8a7b08ac7e44e5ea1ff","isMergeCommit":false,"messageTitle":"Support new datetime formats","messageBody":"","fileTypesAndContributionMap":{"java":{"insertions":15,"deletions":9}}},{"hash":"0ff86cb5fc414fe91a7a3cf21959e4dd283de6b1","isMergeCommit":true,"messageTitle":"Merge branch \u0027branch-Level-8\u0027 with \u0027main\u0027","messageBody":"","tags":["Level-8"],"fileTypesAndContributionMap":{}}]},{"date":"2026-02-04T00:00:00","commitResults":[{"hash":"25e7b1cca1e6c1ab832fbcf6a336d3d875b7abae","isMergeCommit":false,"messageTitle":"Add Ui class to handle user input and output","messageBody":"","fileTypesAndContributionMap":{"java":{"insertions":279,"deletions":140}}},{"hash":"f176effa2e511530fc4c256cddf4504b95bf3aa9","isMergeCommit":false,"messageTitle":"Add TaskList class to handle taskList operations","messageBody":"","fileTypesAndContributionMap":{"java":{"insertions":157,"deletions":36}}}]},{"date":"2026-02-06T00:00:00","commitResults":[{"hash":"df53d842baa4bb1a3670432fb8b8b95953fe70bd","isMergeCommit":false,"messageTitle":"Extract input parsing functionality into InputParser class","messageBody":"","fileTypesAndContributionMap":{"java":{"insertions":225,"deletions":166}}},{"hash":"9edeeef948073b479ce0e111ee1b3e931a7a893a","isMergeCommit":false,"messageTitle":"Add Command class to handle command behaviour","messageBody":"","fileTypesAndContributionMap":{"txt":{"insertions":8,"deletions":6},"bat":{"insertions":1,"deletions":1}}},{"hash":"349d34b8a80357b9c312042fd0638c6692ea4c94","isMergeCommit":false,"messageTitle":"Add Command class to handle command behaviour","messageBody":"","fileTypesAndContributionMap":{"java":{"insertions":249,"deletions":140}}},{"hash":"4b9d62118d01a640975c93f252eacfcde1617d3e","isMergeCommit":true,"messageTitle":"Merge branch \u0027branch-MoreOOP\u0027 into \u0027master\u0027","messageBody":"","tags":["A-MoreOOP"],"fileTypesAndContributionMap":{}},{"hash":"8fa688126f4e73cbcbe99844ead89634d6b3791a","isMergeCommit":false,"messageTitle":"Organize classes into Java packages","messageBody":"","tags":["A-Packages"],"fileTypesAndContributionMap":{"java":{"insertions":83,"deletions":0}}},{"hash":"f7d6d18a0df41995d0476a6ed9a61454bb4353e3","isMergeCommit":true,"messageTitle":"Merge remote-tracking branch \u0027origin/add-gradle-support\u0027 into \u0027master\u0027","messageBody":"","fileTypesAndContributionMap":{}},{"hash":"bed90ac5a04f76a6a50bb6d4e63b93a4be2d7b9a","isMergeCommit":false,"messageTitle":"Add gradle support","messageBody":"","tags":["A-Gradle"],"fileTypesAndContributionMap":{"gradle":{"insertions":3,"deletions":2}}}]},{"date":"2026-02-09T00:00:00","commitResults":[{"hash":"bc566aff12cbd98d719bca9b915f5e03d6861218","isMergeCommit":false,"messageTitle":"Add JUnit test for Parsers and Event Task","messageBody":"","tags":["A-JUnit"],"fileTypesAndContributionMap":{"java":{"insertions":147,"deletions":0}}},{"hash":"93076c1b8fb8326283185bf8a8019f84a8698339","isMergeCommit":false,"messageTitle":"Fix LocalDateTime parsing logic","messageBody":"","fileTypesAndContributionMap":{"java":{"insertions":12,"deletions":12}}},{"hash":"51ad3cc0eaf7fa7bfc54d133f0ef8f6a1cffd309","isMergeCommit":false,"messageTitle":"Modify build.gradle to create JAR file","messageBody":"","tags":["A-Jar"],"fileTypesAndContributionMap":{"gradle":{"insertions":1,"deletions":0}}},{"hash":"491c74f59ea0aeafdcb4da87e5754cfad6af3470","isMergeCommit":false,"messageTitle":"Add JavaDoc comments","messageBody":"","fileTypesAndContributionMap":{"java":{"insertions":195,"deletions":11}}},{"hash":"e7f4b585c9b199cac1a80df736983505b14abc35","isMergeCommit":true,"messageTitle":"Merge branch \u0027branch-A-JavaDoc\u0027","messageBody":"","tags":["A-JavaDoc"],"fileTypesAndContributionMap":{}},{"hash":"d52d0bdbd1f13e5fad9a9e0245467a579923b73e","isMergeCommit":false,"messageTitle":"Modify code to comply with coding standard","messageBody":"","fileTypesAndContributionMap":{"java":{"insertions":89,"deletions":93}}},{"hash":"ecdb7d0326b06a98dd2696f9f2582fd9119add2c","isMergeCommit":true,"messageTitle":"Merge branch \u0027branch-A-CodingStandard\u0027","messageBody":"","tags":["A-CodingStandard"],"fileTypesAndContributionMap":{}}]},{"date":"2026-02-10T00:00:00","commitResults":[{"hash":"ce4297604a165376af991f2b74f0a2e4245ba3b4","isMergeCommit":false,"messageTitle":"Add find command","messageBody":"","tags":["Level-9"],"fileTypesAndContributionMap":{"java":{"insertions":91,"deletions":5}}},{"hash":"88cfd5324505f6f149ed744dc368ad859e860fbb","isMergeCommit":true,"messageTitle":"Merge branch \u0027branch-Level-9\u0027","messageBody":"","fileTypesAndContributionMap":{}}]},{"date":"2026-02-12T00:00:00","commitResults":[{"hash":"cf720432c7cb15667a33fd2fbe77b5b1af3d57d6","isMergeCommit":false,"messageTitle":"Add checkstyle","messageBody":"","tags":["A-CheckStyle"],"fileTypesAndContributionMap":{"java":{"insertions":103,"deletions":102}}}]},{"date":"2026-02-13T00:00:00","commitResults":[{"hash":"bd61053ed8ead137a041eed91c41b121114e5267","isMergeCommit":false,"messageTitle":"Add JavaFX dependencies","messageBody":"","fileTypesAndContributionMap":{"gradle":{"insertions":15,"deletions":0}}}]},{"date":"2026-02-18T00:00:00","commitResults":[{"hash":"2f14cf8ff4621ed173f73ec9df981ed41dff5d4f","isMergeCommit":false,"messageTitle":"Add basic GUI","messageBody":"","fileTypesAndContributionMap":{"gradle":{"insertions":1,"deletions":1},"java":{"insertions":239,"deletions":3}}},{"hash":"7ca350e88f6965a4759fdf09a88bfddc57392e72","isMergeCommit":false,"messageTitle":"Add FXML and full functionality","messageBody":"","tags":["A-Personality"],"fileTypesAndContributionMap":{"fxml":{"insertions":65,"deletions":0},"java":{"insertions":221,"deletions":205}}},{"hash":"ef34c9ed4181bcac6d992f5830d43b16f8c9cc2e","isMergeCommit":false,"messageTitle":"Add styling for GUI","messageBody":"","tags":["A-BetterGUI"],"fileTypesAndContributionMap":{"fxml":{"insertions":13,"deletions":37},"java":{"insertions":54,"deletions":10}}},{"hash":"a5225c9cbaa0f4b944697de3ef5cdbf6d7b1c7d6","isMergeCommit":false,"messageTitle":"Add GUI closing using bye command","messageBody":"","fileTypesAndContributionMap":{"java":{"insertions":16,"deletions":0}}},{"hash":"e1a008f0c65ae09f5f0e0ee82833d3272ff54ef3","isMergeCommit":true,"messageTitle":"Merge branch \u0027branch-Level-10\u0027","messageBody":"","tags":["Level-10"],"fileTypesAndContributionMap":{}},{"hash":"b2a304e69624ebe5e782918627083daa3f06e295","isMergeCommit":false,"messageTitle":"Fix styling","messageBody":"","fileTypesAndContributionMap":{"java":{"insertions":5,"deletions":2}}},{"hash":"22a548e6868250e55ba8aff8fa39d538b7f7a1f8","isMergeCommit":false,"messageTitle":"Add assertions","messageBody":"Assertions help to ensure that my assumed invariants are correct during\nruntime.\n\nLet\u0027s add assertions to the following files\n* Task.java, Deadline.java, Event.java: Ensure that fields are not null\n  after construction\n* TaskList.java: Ensure that indices for task operations are within\n  bounds\n* Storage.java: Ensure that tasks loaded from the data file are\n  formatted correctly\n","fileTypesAndContributionMap":{"java":{"insertions":10,"deletions":0}}},{"hash":"0f92f4eb7e32e44f57f91ee7a44250318cb0692e","isMergeCommit":false,"messageTitle":"Refactor InputParser","messageBody":"The method parseInput within InputParser was too long (originally had\n100+ LoC).\n\nLet\u0027s extract out each individual command parser as its own method.\n\nThis helps to shorten the method and also maintain SLAP.\n\nDoing so is preferable as it is easier for developers to modify\nbehaviour of certain commands.\n","tags":["A-FullCommitMessage"],"fileTypesAndContributionMap":{"java":{"insertions":88,"deletions":89}}},{"hash":"6f20b3369bbccd2032c26318a8ea9b6a24524532","isMergeCommit":false,"messageTitle":"Add more supported DateTime formats","messageBody":"Provides more flexibility for users to enter varying DateTime formats,\nmore tolerant of spaces added within the given DateTime string.\n\nLet\u0027s add 3 more formats, allowing users to enter 12-hour format timings\nwithout the space before \"AM/PM\".\n","fileTypesAndContributionMap":{"java":{"insertions":7,"deletions":0}}},{"hash":"65c3887795d9ee7a826d04fbc0a03cd59e48b4fb","isMergeCommit":false,"messageTitle":"Remove dead code and irrelevant header comment","messageBody":"","fileTypesAndContributionMap":{"java":{"insertions":2,"deletions":8}}}]},{"date":"2026-02-19T00:00:00","commitResults":[{"hash":"4261de79ef5194d8385ff52c9c8a89439261425e","isMergeCommit":false,"messageTitle":"Refactor loadTasks method","messageBody":"The loadTasks method was too long (50+ LoC) and this affected\nreadability.\n\nLet\u0027s extract out the task parsing into a separate method\nparseTaskFromLine.\n","fileTypesAndContributionMap":{"java":{"insertions":32,"deletions":31}}},{"hash":"df5d7fcfe59339129b895e6fe216ac7326932df4","isMergeCommit":true,"messageTitle":"Merge branch \u0027branch-A-Assertions\u0027","messageBody":"","fileTypesAndContributionMap":{}},{"hash":"e3f4e4895078bd369e2f452d917b631029388fcf","isMergeCommit":true,"messageTitle":"Merge branch \u0027master\u0027 into branch-A-CodeQuality","messageBody":"","fileTypesAndContributionMap":{}},{"hash":"76393c43a5a5c926fadb9b84c15f4d98c561db3a","isMergeCommit":true,"messageTitle":"Merge branch \u0027branch-A-CodeQuality\u0027","messageBody":"","fileTypesAndContributionMap":{}},{"hash":"a9a1e6dbc4a7ce27c695dcf7fd63b249a541840b","isMergeCommit":false,"messageTitle":"Revert \"Merge branch \u0027branch-A-CodeQuality\u0027\"","messageBody":"This reverts commit 76393c43a5a5c926fadb9b84c15f4d98c561db3a, reversing\nchanges made to df5d7fcfe59339129b895e6fe216ac7326932df4.\n","fileTypesAndContributionMap":{"java":{"insertions":130,"deletions":131}}},{"hash":"14e9da215965c1ce3e42d1e2411a95d8c0ba6f5b","isMergeCommit":false,"messageTitle":"Revert \"Merge branch \u0027branch-A-Assertions\u0027\"","messageBody":"This reverts commit df5d7fcfe59339129b895e6fe216ac7326932df4, reversing\nchanges made to b2a304e69624ebe5e782918627083daa3f06e295.\n","fileTypesAndContributionMap":{"java":{"insertions":0,"deletions":10}}},{"hash":"525702aa09ce853541609acd42fada204e4026f7","isMergeCommit":false,"messageTitle":"Add assertion for GladosException","messageBody":"","fileTypesAndContributionMap":{"java":{"insertions":1,"deletions":0}}},{"hash":"1254dc9ee763cf7c1e43a5add4f7d165220980c2","isMergeCommit":true,"messageTitle":"Merge pull request #2 from EnderSky/branch-A-Assertions","messageBody":"Add assertion for GladosException","tags":["A-Assertions"],"fileTypesAndContributionMap":{}},{"hash":"75ff1c6377fea73412b79716c089c2e150d03b28","isMergeCommit":true,"messageTitle":"Merge branch \u0027master\u0027 into branch-A-CodeQuality","messageBody":"","fileTypesAndContributionMap":{}},{"hash":"1eb99cbeb7cb1ce746ab51f0825b999e06687954","isMergeCommit":false,"messageTitle":"Reapply \"Merge branch \u0027branch-A-Assertions\u0027\"","messageBody":"This reverts commit 14e9da215965c1ce3e42d1e2411a95d8c0ba6f5b.\n","fileTypesAndContributionMap":{"java":{"insertions":10,"deletions":0}}},{"hash":"7184f3d67840d6f8feddb8fee13548e0c13fbc09","isMergeCommit":false,"messageTitle":"Reapply \"Merge branch \u0027branch-A-CodeQuality\u0027\"","messageBody":"This reverts commit a9a1e6dbc4a7ce27c695dcf7fd63b249a541840b.\n","fileTypesAndContributionMap":{"java":{"insertions":131,"deletions":130}}},{"hash":"20c59f05b354b1af952ba32885fd7e174bc98721","isMergeCommit":true,"messageTitle":"Merge branch \u0027master\u0027 into branch-A-CodeQuality","messageBody":"","fileTypesAndContributionMap":{}},{"hash":"47885031ceeec92b3b90c71de786712948c831b6","isMergeCommit":false,"messageTitle":"Refactor saveTasks method","messageBody":"The saveTasks method is slightly long (30+ LoC) so refactoring it can\nimprove readability.\n\nLet\u0027s extract out the portion of code to create the file and its parent\ndirectories if they do not exist.\n\nThere are now 2 levels of abstraction within the code but this doesn\u0027t\naffect readability as there is sufficient spacing between the\ncreateFileIfNotExists function call and the subsequent code.\n\nAdditionally, the createFileIfNotExists function is a helper function,\nwhich doesn\u0027t detract from the main functionality. Hence, SLAP is still\npreserved.\n","fileTypesAndContributionMap":{"java":{"insertions":17,"deletions":14}}},{"hash":"12f2f785bb8d406d1385e653b7429643f33a46fe","isMergeCommit":true,"messageTitle":"Merge pull request #3 from EnderSky/branch-A-CodeQuality","messageBody":"Branch A-CodeQuality","tags":["A-CodeQuality"],"fileTypesAndContributionMap":{}},{"hash":"42e8dbfca62592b2d7c5e47dac45ba63a5788480","isMergeCommit":false,"messageTitle":"Add remindme command to group deadlines by time","messageBody":"","tags":["A-Streams"],"fileTypesAndContributionMap":{"java":{"insertions":103,"deletions":0}}},{"hash":"0ec65a6adf1d07075381804299750678088e4f04","isMergeCommit":false,"messageTitle":"Add deadline group formatting using Copilot","messageBody":"","tags":["A-AiAssisted"],"fileTypesAndContributionMap":{"java":{"insertions":10,"deletions":8}}},{"hash":"a52fb47274cbdf9bf040421db645d932d6d323a2","isMergeCommit":false,"messageTitle":"Add DeadlineCategory enums to replace strings","messageBody":"","fileTypesAndContributionMap":{"java":{"insertions":36,"deletions":12}}},{"hash":"1443333d712997c242d2d0c86e12481fb2517504","isMergeCommit":false,"messageTitle":"Fix checkstyle","messageBody":"","tags":["BCD-Extension"],"fileTypesAndContributionMap":{"java":{"insertions":9,"deletions":5}}},{"hash":"1a50b4ad56ccc4f2623e7f1b43930a5712e59705","isMergeCommit":false,"messageTitle":"Add help command","messageBody":"","tags":["C-Help"],"fileTypesAndContributionMap":{"java":{"insertions":46,"deletions":14}}},{"hash":"7e1d733d625515d7c7e6fab9262b500f44bc686a","isMergeCommit":false,"messageTitle":"Remove welcome logo","messageBody":"","fileTypesAndContributionMap":{"java":{"insertions":11,"deletions":4}}},{"hash":"f170eeb54e0820446eb6a573ecfef6a3d3a24159","isMergeCommit":false,"messageTitle":"Fix remindme command","messageBody":"","fileTypesAndContributionMap":{"java":{"insertions":4,"deletions":2}}}]}]},"authorFileTypeContributionMap":{"EnderSky":{"java":1954,"md":16,"fxml":41,"sh":0,"bat":1,"gradle":19,"txt":11}},"authorContributionVariance":{"EnderSky":73812.586},"authorDisplayNameMap":{"EnderSky":"CS2103T-F14-2 JOTH..IANG"}}
